LICENSE
MANIFEST.in
README.rst
setup.py
./PEPPAN.py
./PEPPAN_parser.py
./__init__.py
PEPPAN.egg-info/PKG-INFO
PEPPAN.egg-info/SOURCES.txt
PEPPAN.egg-info/dependency_links.txt
PEPPAN.egg-info/entry_points.txt
PEPPAN.egg-info/requires.txt
PEPPAN.egg-info/top_level.txt
dependencies/FastTreeMP
dependencies/blastn
dependencies/diamond
dependencies/makeblastdb
dependencies/mmseqs
dependencies/rapidnj
modules/clust.py
modules/configure.py
modules/uberBlast.py