Metadata-Version: 2.1
Name: PEPPAN
Version: 1.0.6
Summary: Phylogeny Enhanded Prediction of PAN-genome https://doi.org/10.1101/2020.01.03.894154
Home-page: https://github.com/zheminzhou/PEPPAN
Author: Zhemin Zhou
Author-email: zhemin.zhou@warwick.ac.uk
License: UNKNOWN
Keywords: bioinformatics,microbial,genomics,MLST,pan-genome
Platform: UNKNOWN
Classifier: Development Status :: 5 - Production/Stable
Classifier: Programming Language :: Python :: 3.5
Classifier: Programming Language :: Python :: 3.6
Classifier: Programming Language :: Python :: 3.7
Classifier: Programming Language :: Python :: 3.8
Classifier: License :: OSI Approved :: GNU General Public License v3 (GPLv3)
Classifier: Operating System :: OS Independent
